qiime2utils/__init__.py
qiime2utils/main.py
qiime2utils/qiime2utils
qiime2utils-0.0.11.data/scripts/qiime2utils
qiime2utils-0.0.11.dist-info/LICENSE
qiime2utils-0.0.11.dist-info/METADATA
qiime2utils-0.0.11.dist-info/WHEEL
qiime2utils-0.0.11.dist-info/top_level.txt
qiime2utils-0.0.11.dist-info/RECORD
